QFinance/__init__.py
QFinance/algorithms/QFT.py
QFinance/algorithms/__init__.py
QFinance/algorithms/comparator.py
QFinance/algorithms/monte_carlo.py
QFinance/algorithms/prepare_state.py
QFinance/algorithms/amplitude_estimation/AE_problem.py
QFinance/algorithms/amplitude_estimation/IQAE.py
QFinance/algorithms/amplitude_estimation/MLAE.py
QFinance/algorithms/amplitude_estimation/QAE.py
QFinance/algorithms/amplitude_estimation/__init__.py
QFinance/algorithms/linear_function/__init__.py
QFinance/algorithms/linear_function/linear.py
QFinance/algorithms/linear_function/piecewise_linear.py
QFinance/algorithms/phase_estimation/QPE.py
QFinance/algorithms/phase_estimation/__init__.py
QFinance/gui/test.py
QFinance/pricing/__init__.py
QFinance/pricing/demo.py
QFinance/pricing/lognormal.py
QFinance/pricing/option_pricing.py
QFinance/pricing/option_pricing_classical.py
QFinance/utils/__init__.py
QFinance/utils/measure.py
QFinance/utils/multi_control.py
QFinance/utils/subQReg.py
qfinance-1.0.3.dist-info/LICENSE
qfinance-1.0.3.dist-info/METADATA
qfinance-1.0.3.dist-info/WHEEL
qfinance-1.0.3.dist-info/top_level.txt
qfinance-1.0.3.dist-info/RECORD
