Metadata-Version: 2.1
Name: qfinance
Version: 1.0.3
Summary: Quantum Finance Library
License: Copyright (c) 2023 Baidu, Inc. All Rights Reserved.
Requires-Python: >=3.9
License-File: LICENSE
Requires-Dist: qcompute (>=3.3.0)
